{
    "rating": 1594,
    "code": "SVN",
    "thumbnail": "thumbnail.png",
    "flag": "flag.png",
    "flag_thumbnail": "flag_thumbnail.png",
    "continent": "europe",
    "kits": {
        "goalkeeper": {
            "arm_left_sleeve": {
                "name": "goalkeeper/sleeve_left.png",
                "color": "ffffffff",
                "x": 8.88,
                "y": -2.01,
                "rotation": 76.85,
                "width": 14,
                "height": 22
            },
            "arm_right_sleeve": {
                "name": "goalkeeper/sleeve_right.png",
                "color": "ffffffff",
                "x": 8.04,
                "y": -1.78,
                "rotation": 130.74,
                "width": 23,
                "height": 18
            },
            "shirt_back": {
                "name": "../../player/kit/shirt_back.png",
                "color": "8e8e8eff",
                "x": 24.8,
                "y": 1.45,
                "rotation": -88.19,
                "width": 56,
                "height": 52
            },
            "shirt_front": {
                "name": "goalkeeper/shirt_front.png",
                "x": 24.8,
                "y": 1.45,
                "rotation": -88.19,
                "width": 56,
                "height": 52,
                "color": "ffffffff"
            },
            "leg_left_shoe": {
                "name": "../../player/kit/shoes.png",
                "color": "666666ff",
                "x": 4.62,
                "y": 0.29,
                "rotation": 0.35,
                "width": 16,
                "height": 6
            },
            "leg_left_shorts": {
                "name": "../../player/kit/shorts_leg.png",
                "color": "17181aff",
                "x": 2.61,
                "y": 0.45,
                "rotation": 80.83,
                "width": 12,
                "height": 16
            },
            "leg_left_sock": {
                "name": "../../player/kit/socks.png",
                "color": "8f8f8fff",
                "x": 6.76,
                "y": 0.63,
                "rotation": 110.26,
                "width": 11,
                "height": 14
            },
            "leg_right_shoe": {
                "name": "../../player/kit/shoes.png",
                "color": "666666ff",
                "x": 3.8,
                "y": -0.26,
                "rotation": 4.17,
                "width": 16,
                "height": 6
            },
            "leg_right_shorts": {
                "name": "../../player/kit/shorts_leg.png",
                "color": "17181aff",
                "x": 1.14,
                "y": 0.39,
                "rotation": 81.11,
                "width": 12,
                "height": 16
            },
            "leg_right_sock": {
                "name": "../../player/kit/socks.png",
                "color": "8f8f8fff",
                "x": 5.51,
                "y": 0.76,
                "rotation": 110.01,
                "width": 11,
                "height": 14
            },
            "number": {
                "name": "../../player/kit/number.png",
                "color": "000000ff",
                "x": 17.18,
                "y": 0.16,
                "rotation": -89.44,
                "width": 33,
                "height": 18
            },
            "pelvis_shorts": {
                "name": "../../player/kit/shorts.png",
                "color": "17181aff",
                "x": -1.27,
                "y": 0.02,
                "width": 55,
                "height": 8
            },
            "hand_left_glove": {
                "name": "goalkeeper/hand_left.png",
                "x": 20.29,
                "y": -0.1,
                "rotation": 44.65,
                "width": 26,
                "height": 24
            },
            "hand_right_glove": {
                "name": "goalkeeper/hand_right.png",
                "x": 18.57,
                "y": -0.32,
                "rotation": 74.29,
                "width": 26,
                "height": 25
            }
        },
        "home": {
            "arm_left_sleeve": {
                "name": "home/sleeve_left.png",
                "color": "ffffffff",
                "x": 8.88,
                "y": -2.01,
                "rotation": 76.85,
                "width": 14,
                "height": 22
            },
            "arm_right_sleeve": {
                "name": "home/sleeve_right.png",
                "color": "ffffffff",
                "x": 8.04,
                "y": -1.78,
                "rotation": 130.74,
                "width": 23,
                "height": 18
            },
            "shirt_back": {
                "name": "../../player/kit/shirt_back.png",
                "color": "a60000ff",
                "x": 24.8,
                "y": 1.45,
                "rotation": -88.19,
                "width": 56,
                "height": 52
            },
            "shirt_front": {
                "name": "home/shirt_front.png",
                "color": "ffffffff",
                "x": 24.8,
                "y": 1.45,
                "rotation": -88.19,
                "width": 56,
                "height": 52
            },
            "leg_left_shoe": {
                "name": "../../player/kit/shoes.png",
                "color": "666666ff",
                "x": 4.62,
                "y": 0.29,
                "rotation": 0.35,
                "width": 16,
                "height": 6
            },
            "leg_left_shorts": {
                "name": "../../player/kit/shorts_leg.png",
                "color": "e7e8edff",
                "x": 2.61,
                "y": 0.45,
                "rotation": 80.83,
                "width": 12,
                "height": 16
            },
            "leg_left_sock": {
                "name": "home/socks.png",
                "color": "ffffffff",
                "x": 6.76,
                "y": 0.63,
                "rotation": 110.26,
                "width": 11,
                "height": 14
            },
            "leg_right_shoe": {
                "name": "../../player/kit/shoes.png",
                "color": "666666ff",
                "x": 3.8,
                "y": -0.26,
                "rotation": 4.17,
                "width": 16,
                "height": 6
            },
            "leg_right_shorts": {
                "name": "../../player/kit/shorts_leg.png",
                "color": "e7e8edff",
                "x": 1.14,
                "y": 0.39,
                "rotation": 81.11,
                "width": 12,
                "height": 16
            },
            "leg_right_sock": {
                "name": "home/socks.png",
                "color": "ffffffff",
                "x": 5.51,
                "y": 0.76,
                "rotation": 110.01,
                "width": 11,
                "height": 14
            },
            "number": {
                "name": "../../player/kit/number.png",
                "color": "ffffffff",
                "x": 17.18,
                "y": 0.16,
                "rotation": -89.44,
                "width": 33,
                "height": 18
            },
            "pelvis_shorts": {
                "name": "../../player/kit/shorts.png",
                "color": "e7e8edff",
                "x": -1.27,
                "y": 0.02,
                "width": 55,
                "height": 8
            }
        },
        "away": {
            "arm_left_sleeve": {
                "name": "away/sleeve_left.png",
                "color": "ffffffff",
                "x": 8.88,
                "y": -2.01,
                "rotation": 76.85,
                "width": 14,
                "height": 22
            },
            "arm_right_sleeve": {
                "name": "away/sleeve_right.png",
                "color": "ffffffff",
                "x": 8.04,
                "y": -1.78,
                "rotation": 130.74,
                "width": 23,
                "height": 18
            },
            "shirt_back": {
                "name": "../../player/kit/shirt_back.png",
                "color": "e7e8edff",
                "x": 24.8,
                "y": 1.45,
                "rotation": -88.19,
                "width": 56,
                "height": 52
            },
            "shirt_front": {
                "name": "away/shirt_front.png",
                "color": "ffffffff",
                "x": 24.8,
                "y": 1.45,
                "rotation": -88.19,
                "width": 56,
                "height": 52
            },
            "leg_left_shoe": {
                "name": "../../player/kit/shoes.png",
                "color": "666666ff",
                "x": 4.62,
                "y": 0.29,
                "rotation": 0.35,
                "width": 16,
                "height": 6
            },
            "leg_left_shorts": {
                "name": "../../player/kit/shorts_leg.png",
                "color": "004e8aff",
                "x": 2.61,
                "y": 0.45,
                "rotation": 80.83,
                "width": 12,
                "height": 16
            },
            "leg_left_sock": {
                "name": "away/socks.png",
                "color": "ffffffff",
                "x": 6.76,
                "y": 0.63,
                "rotation": 110.26,
                "width": 11,
                "height": 14
            },
            "leg_right_shoe": {
                "name": "../../player/kit/shoes.png",
                "color": "666666ff",
                "x": 3.8,
                "y": -0.26,
                "rotation": 4.17,
                "width": 16,
                "height": 6
            },
            "leg_right_shorts": {
                "name": "../../player/kit/shorts_leg.png",
                "color": "004e8aff",
                "x": 1.14,
                "y": 0.39,
                "rotation": 81.11,
                "width": 12,
                "height": 16
            },
            "leg_right_sock": {
                "name": "away/socks.png",
                "color": "ffffffff",
                "x": 5.51,
                "y": 0.76,
                "rotation": 110.01,
                "width": 11,
                "height": 14
            },
            "number": {
                "name": "../../player/kit/number.png",
                "color": "a60000ff",
                "x": 17.18,
                "y": 0.16,
                "rotation": -89.44,
                "width": 33,
                "height": 18
            },
            "pelvis_shorts": {
                "name": "../../player/kit/shorts.png",
                "color": "004e8aff",
                "x": -1.27,
                "y": 0.02,
                "width": 55,
                "height": 8
            }
        }
    },
    "id": "slovenia",
    "kitColors": {
        "home": "a60000",
        "away": "e7e8ed"
    },
    "players": [
        {
            "race": "caucasian",
            "role": "G",
            "skin": {
                "eyebrows": {
                    "name": "../../player/eyebrows/30.png",
                    "color": "301f12ff",
                    "x": 38.735680037250376,
                    "y": -13.003199656797712,
                    "rotation": -90.13,
                    "width": 36,
                    "height": 6
                },
                "eyes": {
                    "name": "../../player/eyes/04.png",
                    "x": 34.29681192627471,
                    "y": -12.705469869886597,
                    "rotation": -90.13,
                    "width": 41,
                    "height": 14
                },
                "eyes_closed": {
                    "name": "../../player/eyes/closed/closed.png",
                    "x": 34.7934072501454,
                    "y": -14.206600471902881,
                    "rotation": -90.13,
                    "width": 38,
                    "height": 12
                },
                "eyes_dead": {
                    "name": "../../player/eyes/dead/dead.png",
                    "x": 32.29454814822605,
                    "y": -13.700929443708826,
                    "rotation": -90.13,
                    "width": 60,
                    "height": 40
                },
                "hair_front": {
                    "name": "../../player/hair/49.png",
                    "color": "4d3629ff",
                    "x": 52.65531517221957,
                    "y": -5.0060375994684065,
                    "rotation": -90.13,
                    "width": 71,
                    "height": 51
                },
                "hair_back": {
                    "name": "../../player/hair/49_back.png",
                    "color": "4d3629ff",
                    "x": 37.32277761582659,
                    "y": -4.637914924234261,
                    "rotation": -90.13,
                    "width": 72,
                    "height": 84
                },
                "mouth_normal": {
                    "name": "../../player/mouth/12.png",
                    "x": 4.215676176226239,
                    "y": -12.376603045918973,
                    "rotation": -90.13,
                    "width": 18,
                    "height": 4
                },
                "mouth_smile": {
                    "name": "../../player/mouth/smile/01.png",
                    "x": 5.71,
                    "y": -14.88,
                    "rotation": -90.13,
                    "width": 32,
                    "height": 8
                },
                "mouth_dead": {
                    "name": "../../player/mouth/dead/01.png",
                    "x": 5.71,
                    "y": -14.88,
                    "rotation": -90.13,
                    "width": 23,
                    "height": 16
                },
                "nose": {
                    "name": "../../player/nose/27.png",
                    "color": "3e72adff",
                    "x": 23.60453527814559,
                    "y": -14.212274074113026,
                    "rotation": -90.13,
                    "width": 17,
                    "height": 20
                },
                "face_accessory_2": {
                    "name": "../../player/accessories/face/beard_06.png",
                    "color": "544035ff",
                    "x": 7.730415186695374,
                    "y": -5.884561018306517,
                    "rotation": -90.13,
                    "width": 72,
                    "height": 47
                }
            }
        },
        {
            "race": "caucasian",
            "role": "D",
            "skin": {
                "eyebrows": {
                    "name": "../../player/eyebrows/01.png",
                    "color": "61402dff",
                    "x": 39.48681256977873,
                    "y": -12.504902638366389,
                    "rotation": -90.13,
                    "width": 42,
                    "height": 5
                },
                "eyes": {
                    "name": "../../player/eyes/28.png",
                    "x": 31.800221750436197,
                    "y": -11.19980141570864,
                    "rotation": -90.13,
                    "width": 41,
                    "height": 13
                },
                "eyes_closed": {
                    "name": "../../player/eyes/closed/closed.png",
                    "x": 33.2968145002908,
                    "y": -12.70320094380576,
                    "rotation": -90.13,
                    "width": 38,
                    "height": 12
                },
                "eyes_dead": {
                    "name": "../../player/eyes/dead/dead.png",
                    "x": 30.795686472290612,
                    "y": -13.197527341595613,
                    "rotation": -90.13,
                    "width": 60,
                    "height": 40
                },
                "hair_front": {
                    "name": "../../player/hair/29.png",
                    "color": "875d46ff",
                    "x": 49.49092558268469,
                    "y": -3.9988552408952085,
                    "rotation": -90.13,
                    "width": 76,
                    "height": 46
                },
                "hair_back": {
                    "name": "../../player/hair/29_back.png",
                    "color": "875d46ff",
                    "x": 32.99210251699064,
                    "y": -3.4614192475693963,
                    "rotation": -90.13,
                    "width": 76,
                    "height": 81
                },
                "mouth_normal": {
                    "name": "../../player/mouth/03B.png",
                    "x": 5.71,
                    "y": -14.88,
                    "rotation": -90.13,
                    "width": 29,
                    "height": 6
                },
                "mouth_smile": {
                    "name": "../../player/mouth/smile/01.png",
                    "x": 3.214544287201912,
                    "y": -12.874332832830087,
                    "rotation": -90.13,
                    "width": 32,
                    "height": 8
                },
                "mouth_dead": {
                    "name": "../../player/mouth/dead/01.png",
                    "x": 2.2145468612180053,
                    "y": -12.872063906749247,
                    "rotation": -90.13,
                    "width": 23,
                    "height": 16
                },
                "nose": {
                    "name": "../../player/nose/01.png",
                    "color": "9c1000ff",
                    "x": 17.857386236339174,
                    "y": -12.949230966668313,
                    "rotation": -90.13,
                    "width": 16,
                    "height": 21
                },
                "face_accessory_2": {
                    "name": "../../player/accessories/face/beard_02.png",
                    "color": "ffffffff",
                    "x": 10.731920082034314,
                    "y": -5.224702845893112,
                    "rotation": -90.13,
                    "width": 70,
                    "height": 44
                }
            }
        },
        {
            "race": "caucasian",
            "role": "D",
            "skin": {
                "eyebrows": {
                    "name": "../../player/eyebrows/22.png",
                    "color": "8c7124ff",
                    "x": 39.7424842414768,
                    "y": -10.00547630492683,
                    "rotation": -90.13,
                    "width": 36,
                    "height": 4
                },
                "eyes": {
                    "name": "../../player/eyes/07.png",
                    "x": 31.055328764630154,
                    "y": -8.948105512684219,
                    "rotation": -90.13,
                    "width": 38,
                    "height": 12
                },
                "eyes_closed": {
                    "name": "../../player/eyes/closed/closed.png",
                    "x": 32.802488102500945,
                    "y": -10.202072915805573,
                    "rotation": -90.13,
                    "width": 38,
                    "height": 12
                },
                "eyes_dead": {
                    "name": "../../player/eyes/dead/dead.png",
                    "x": 29.30136264851685,
                    "y": -10.694130387514587,
                    "rotation": -90.13,
                    "width": 60,
                    "height": 40
                },
                "hair_front": {
                    "name": "../../player/hair/52.png",
                    "color": "dbaa40ff",
                    "x": 52.493186786717246,
                    "y": -3.0056645931538206,
                    "rotation": -90.13,
                    "width": 70,
                    "height": 57
                },
                "hair_back": {
                    "name": "../../player/hair/52_back.png",
                    "color": "dbaa40ff",
                    "x": 36.99209222092627,
                    "y": -3.470494951892756,
                    "rotation": -90.13,
                    "width": 71,
                    "height": 87
                },
                "mouth_normal": {
                    "name": "../../player/mouth/08.png",
                    "x": 5.970209523859756,
                    "y": -10.38057881459263,
                    "rotation": -90.13,
                    "width": 20,
                    "height": 4
                },
                "mouth_smile": {
                    "name": "../../player/mouth/smile/01.png",
                    "x": 4.216810639266659,
                    "y": -11.87660433292702,
                    "rotation": -90.13,
                    "width": 32,
                    "height": 8
                },
                "mouth_dead": {
                    "name": "../../player/mouth/dead/01.png",
                    "x": 3.7224842414768053,
                    "y": -9.375476304926833,
                    "rotation": -90.13,
                    "width": 23,
                    "height": 16
                },
                "nose": {
                    "name": "../../player/nose/08.png",
                    "color": "50708fff",
                    "x": 20.613051472997018,
                    "y": -10.455476948430857,
                    "rotation": -90.13,
                    "width": 18,
                    "height": 17
                }
            }
        },
        {
            "race": "caucasian",
            "role": "M",
            "skin": {
                "eyebrows": {
                    "name": "../../player/eyebrows/26.png",
                    "color": "5c3c27ff",
                    "x": 38.23284516665737,
                    "y": -14.252061976237176,
                    "rotation": -90.13,
                    "width": 35,
                    "height": 5
                },
                "eyes": {
                    "name": "../../player/eyes/10.png",
                    "x": 29.79682350934712,
                    "y": -12.69525970252282,
                    "rotation": -90.13,
                    "width": 43,
                    "height": 15
                },
                "eyes_closed": {
                    "name": "../../player/eyes/closed/closed.png",
                    "x": 32.293413685185634,
                    "y": -14.200928156700781,
                    "rotation": -90.13,
                    "width": 38,
                    "height": 12
                },
                "eyes_dead": {
                    "name": "../../player/eyes/dead/dead.png",
                    "x": 29.79228565718544,
                    "y": -14.695254554490635,
                    "rotation": -90.13,
                    "width": 60,
                    "height": 40
                },
                "hair_front": {
                    "name": "../../player/hair/49.png",
                    "color": "69422eff",
                    "x": 52.65531517221957,
                    "y": -5.0060375994684065,
                    "rotation": -90.13,
                    "width": 71,
                    "height": 51
                },
                "hair_back": {
                    "name": "../../player/hair/49_back.png",
                    "color": "69422eff",
                    "x": 37.32277761582659,
                    "y": -4.637914924234261,
                    "rotation": -90.13,
                    "width": 72,
                    "height": 84
                },
                "mouth_normal": {
                    "name": "../../player/mouth/21.png",
                    "x": 4.2117055555847696,
                    "y": -14.12659854139081,
                    "rotation": -90.13,
                    "width": 26,
                    "height": 4
                },
                "mouth_smile": {
                    "name": "../../player/mouth/smile/01.png",
                    "x": 3.210006435040232,
                    "y": -14.874327684797901,
                    "rotation": -90.13,
                    "width": 32,
                    "height": 8
                },
                "mouth_dead": {
                    "name": "../../player/mouth/dead/01.png",
                    "x": 2.211143472096745,
                    "y": -14.372060045725108,
                    "rotation": -90.13,
                    "width": 23,
                    "height": 16
                },
                "nose": {
                    "name": "../../player/nose/30.png",
                    "color": "228c87ff",
                    "x": 18.852845810161398,
                    "y": -14.951494744716967,
                    "rotation": -90.13,
                    "width": 16,
                    "height": 21
                }
            }
        },
        {
            "race": "caucasian",
            "role": "A",
            "skin": {
                "eyebrows": {
                    "name": "../../player/eyebrows/18.png",
                    "color": "4a2f1dff",
                    "x": 37.235683898274516,
                    "y": -12.999796267676452,
                    "rotation": -90.13,
                    "width": 42,
                    "height": 7
                },
                "eyes": {
                    "name": "../../player/eyes/27.png",
                    "x": 29.796256277826913,
                    "y": -12.945259059018799,
                    "rotation": -90.13,
                    "width": 41,
                    "height": 14
                },
                "eyes_closed": {
                    "name": "../../player/eyes/closed/closed.png",
                    "x": 30.79682093533103,
                    "y": -12.69752862860366,
                    "rotation": -90.13,
                    "width": 38,
                    "height": 12
                },
                "eyes_dead": {
                    "name": "../../player/eyes/dead/dead.png",
                    "x": 27.296829944387355,
                    "y": -12.68958738732072,
                    "rotation": -90.13,
                    "width": 60,
                    "height": 40
                },
                "hair_front": {
                    "name": "../../player/hair/09C.png",
                    "color": "ffffffff",
                    "x": 48.49886939798372,
                    "y": -0.49659532387069366,
                    "rotation": -90.13,
                    "width": 62,
                    "height": 38
                },
                "hair_back": {
                    "name": "../../player/hair/09C_back.png",
                    "color": "ffffffff",
                    "x": 31.487568525853103,
                    "y": -5.458010710415951,
                    "rotation": -90.13,
                    "width": 70,
                    "height": 72
                },
                "mouth_normal": {
                    "name": "../../player/mouth/12.png",
                    "x": 4.215676176226239,
                    "y": -12.376603045918973,
                    "rotation": -90.13,
                    "width": 18,
                    "height": 4
                },
                "mouth_smile": {
                    "name": "../../player/mouth/smile/01.png",
                    "x": 4.215676176226239,
                    "y": -12.376603045918973,
                    "rotation": -90.13,
                    "width": 32,
                    "height": 8
                },
                "mouth_dead": {
                    "name": "../../player/mouth/dead/01.png",
                    "x": 2.216815787298845,
                    "y": -11.87206648076534,
                    "rotation": -90.13,
                    "width": 23,
                    "height": 16
                },
                "nose": {
                    "name": "../../player/nose/07.png",
                    "color": "9c3103ff",
                    "x": 18.358519412371546,
                    "y": -12.450366716716779,
                    "rotation": -90.13,
                    "width": 15,
                    "height": 18
                }
            }
        },
        {
            "race": "caucasian",
            "role": "A",
            "skin": {
                "eyebrows": {
                    "name": "../../player/eyebrows/03.png",
                    "color": "301f15ff",
                    "x": 39.23738044480296,
                    "y": -12.254336050350203,
                    "rotation": -90.13,
                    "width": 37,
                    "height": 7
                },
                "eyes": {
                    "name": "../../player/eyes/01.png",
                    "x": 31.801923444996827,
                    "y": -10.449803346220708,
                    "rotation": -90.13,
                    "width": 41,
                    "height": 17
                },
                "eyes_closed": {
                    "name": "../../player/eyes/closed/closed.png",
                    "x": 32.799084713379685,
                    "y": -11.702069054781433,
                    "rotation": -90.13,
                    "width": 38,
                    "height": 12
                },
                "eyes_dead": {
                    "name": "../../player/eyes/dead/dead.png",
                    "x": 30.79682093533103,
                    "y": -12.69752862860366,
                    "rotation": -90.13,
                    "width": 60,
                    "height": 40
                },
                "hair_front": {
                    "name": "../../player/hair/52.png",
                    "color": "754f37ff",
                    "x": 52.493186786717246,
                    "y": -3.0056645931538206,
                    "rotation": -90.13,
                    "width": 70,
                    "height": 57
                },
                "hair_back": {
                    "name": "../../player/hair/52_back.png",
                    "color": "754f37ff",
                    "x": 36.99209222092627,
                    "y": -3.470494951892756,
                    "rotation": -90.13,
                    "width": 71,
                    "height": 87
                },
                "mouth_normal": {
                    "name": "../../player/mouth/07.png",
                    "x": 4.96680870875459,
                    "y": -11.87830602748765,
                    "rotation": -90.13,
                    "width": 26,
                    "height": 4
                },
                "mouth_smile": {
                    "name": "../../player/mouth/smile/01.png",
                    "x": 4.213407250145399,
                    "y": -13.376600471902881,
                    "rotation": -90.13,
                    "width": 32,
                    "height": 8
                },
                "mouth_dead": {
                    "name": "../../player/mouth/dead/01.png",
                    "x": 2.716814500290799,
                    "y": -11.87320094380576,
                    "rotation": -90.13,
                    "width": 23,
                    "height": 16
                },
                "nose": {
                    "name": "../../player/nose/14.png",
                    "color": "2a4f7aff",
                    "x": 19.35624791227461,
                    "y": -13.452633068781527,
                    "rotation": -90.13,
                    "width": 15,
                    "height": 21
                },
                "face_accessory_2": {
                    "name": "../../player/accessories/face/beard_02.png",
                    "color": "ffffffff",
                    "x": 10.731920082034314,
                    "y": -5.224702845893112,
                    "rotation": -90.13,
                    "width": 70,
                    "height": 44
                }
            }
        }
    ]
}
