{
    "rating": 1401,
    "code": "LIB",
    "thumbnail": "thumbnail.png",
    "flag": "flag.png",
    "flag_thumbnail": "flag_thumbnail.png",
    "continent": "asia",
    "kits": {
        "goalkeeper": {
            "arm_left_sleeve": {
                "name": "goalkeeper/sleeve_left.png",
                "color": "ffffffff",
                "x": 8.88,
                "y": -2.01,
                "rotation": 76.85,
                "width": 14,
                "height": 22
            },
            "arm_right_sleeve": {
                "name": "goalkeeper/sleeve_right.png",
                "color": "ffffffff",
                "x": 8.04,
                "y": -1.78,
                "rotation": 130.74,
                "width": 23,
                "height": 18
            },
            "shirt_back": {
                "name": "../../player/kit/shirt_back.png",
                "color": "8e8e8eff",
                "x": 24.8,
                "y": 1.45,
                "rotation": -88.19,
                "width": 56,
                "height": 52
            },
            "shirt_front": {
                "name": "goalkeeper/shirt_front.png",
                "x": 24.8,
                "y": 1.45,
                "rotation": -88.19,
                "width": 56,
                "height": 52,
                "color": "ffffffff"
            },
            "leg_left_shoe": {
                "name": "../../player/kit/shoes.png",
                "color": "666666ff",
                "x": 4.62,
                "y": 0.29,
                "rotation": 0.35,
                "width": 16,
                "height": 6
            },
            "leg_left_shorts": {
                "name": "../../player/kit/shorts_leg.png",
                "color": "17181aff",
                "x": 2.61,
                "y": 0.45,
                "rotation": 80.83,
                "width": 12,
                "height": 16
            },
            "leg_left_sock": {
                "name": "../../player/kit/socks.png",
                "color": "8f8f8fff",
                "x": 6.76,
                "y": 0.63,
                "rotation": 110.26,
                "width": 11,
                "height": 14
            },
            "leg_right_shoe": {
                "name": "../../player/kit/shoes.png",
                "color": "666666ff",
                "x": 3.8,
                "y": -0.26,
                "rotation": 4.17,
                "width": 16,
                "height": 6
            },
            "leg_right_shorts": {
                "name": "../../player/kit/shorts_leg.png",
                "color": "17181aff",
                "x": 1.14,
                "y": 0.39,
                "rotation": 81.11,
                "width": 12,
                "height": 16
            },
            "leg_right_sock": {
                "name": "../../player/kit/socks.png",
                "color": "8f8f8fff",
                "x": 5.51,
                "y": 0.76,
                "rotation": 110.01,
                "width": 11,
                "height": 14
            },
            "number": {
                "name": "../../player/kit/number.png",
                "color": "000000ff",
                "x": 17.18,
                "y": 0.16,
                "rotation": -89.44,
                "width": 33,
                "height": 18
            },
            "pelvis_shorts": {
                "name": "../../player/kit/shorts.png",
                "color": "17181aff",
                "x": -1.27,
                "y": 0.02,
                "width": 55,
                "height": 8
            },
            "hand_left_glove": {
                "name": "goalkeeper/hand_left.png",
                "x": 20.29,
                "y": -0.1,
                "rotation": 44.65,
                "width": 26,
                "height": 24
            },
            "hand_right_glove": {
                "name": "goalkeeper/hand_right.png",
                "x": 18.57,
                "y": -0.32,
                "rotation": 74.29,
                "width": 26,
                "height": 25
            }
        },
        "home": {
            "arm_left_sleeve": {
                "name": "../../player/kit/sleeve_left.png",
                "color": "c30e2eff",
                "x": 8.88,
                "y": -2.01,
                "rotation": 76.85,
                "width": 14,
                "height": 22
            },
            "arm_right_sleeve": {
                "name": "../../player/kit/sleeve_right.png",
                "color": "c30e2eff",
                "x": 8.04,
                "y": -1.78,
                "rotation": 130.74,
                "width": 23,
                "height": 18
            },
            "shirt_back": {
                "name": "../../player/kit/shirt_back.png",
                "color": "c30e2eff",
                "x": 24.8,
                "y": 1.45,
                "rotation": -88.19,
                "width": 56,
                "height": 52
            },
            "shirt_front": {
                "name": "home/shirt_front.png",
                "color": "ffffffff",
                "x": 24.8,
                "y": 1.45,
                "rotation": -88.19,
                "width": 56,
                "height": 52
            },
            "leg_left_shoe": {
                "name": "../../player/kit/shoes.png",
                "color": "666666ff",
                "x": 4.62,
                "y": 0.29,
                "rotation": 0.35,
                "width": 16,
                "height": 6
            },
            "leg_left_shorts": {
                "name": "../../player/kit/shorts_leg.png",
                "color": "4da56eff",
                "x": 2.61,
                "y": 0.45,
                "rotation": 80.83,
                "width": 12,
                "height": 16
            },
            "leg_left_sock": {
                "name": "home/socks.png",
                "color": "ffffffff",
                "x": 6.76,
                "y": 0.63,
                "rotation": 110.26,
                "width": 11,
                "height": 14
            },
            "leg_right_shoe": {
                "name": "../../player/kit/shoes.png",
                "color": "666666ff",
                "x": 3.8,
                "y": -0.26,
                "rotation": 4.17,
                "width": 16,
                "height": 6
            },
            "leg_right_shorts": {
                "name": "../../player/kit/shorts_leg.png",
                "color": "4da56eff",
                "x": 1.14,
                "y": 0.39,
                "rotation": 81.11,
                "width": 12,
                "height": 16
            },
            "leg_right_sock": {
                "name": "home/socks.png",
                "color": "ffffffff",
                "x": 5.51,
                "y": 0.76,
                "rotation": 110.01,
                "width": 11,
                "height": 14
            },
            "number": {
                "name": "../../player/kit/number.png",
                "color": "ffffffff",
                "x": 17.18,
                "y": 0.16,
                "rotation": -89.44,
                "width": 33,
                "height": 18
            },
            "pelvis_shorts": {
                "name": "../../player/kit/shorts.png",
                "color": "4da56eff",
                "x": -1.27,
                "y": 0.02,
                "width": 55,
                "height": 8
            }
        },
        "away": {
            "arm_left_sleeve": {
                "name": "../../player/kit/sleeve_left.png",
                "color": "e1e2e4ff",
                "x": 8.88,
                "y": -2.01,
                "rotation": 76.85,
                "width": 14,
                "height": 22
            },
            "arm_right_sleeve": {
                "name": "../../player/kit/sleeve_right.png",
                "color": "e1e2e4ff",
                "x": 8.04,
                "y": -1.78,
                "rotation": 130.74,
                "width": 23,
                "height": 18
            },
            "shirt_back": {
                "name": "../../player/kit/shirt_back.png",
                "color": "e1e2e4ff",
                "x": 24.8,
                "y": 1.45,
                "rotation": -88.19,
                "width": 56,
                "height": 52
            },
            "shirt_front": {
                "name": "away/shirt_front.png",
                "color": "ffffffff",
                "x": 24.8,
                "y": 1.45,
                "rotation": -88.19,
                "width": 56,
                "height": 52
            },
            "leg_left_shoe": {
                "name": "../../player/kit/shoes.png",
                "color": "666666ff",
                "x": 4.62,
                "y": 0.29,
                "rotation": 0.35,
                "width": 16,
                "height": 6
            },
            "leg_left_shorts": {
                "name": "../../player/kit/shorts_leg.png",
                "color": "4da56eff",
                "x": 2.61,
                "y": 0.45,
                "rotation": 80.83,
                "width": 12,
                "height": 16
            },
            "leg_left_sock": {
                "name": "away/socks.png",
                "color": "ffffffff",
                "x": 6.76,
                "y": 0.63,
                "rotation": 110.26,
                "width": 11,
                "height": 14
            },
            "leg_right_shoe": {
                "name": "../../player/kit/shoes.png",
                "color": "666666ff",
                "x": 3.8,
                "y": -0.26,
                "rotation": 4.17,
                "width": 16,
                "height": 6
            },
            "leg_right_shorts": {
                "name": "../../player/kit/shorts_leg.png",
                "color": "4da56eff",
                "x": 1.14,
                "y": 0.39,
                "rotation": 81.11,
                "width": 12,
                "height": 16
            },
            "leg_right_sock": {
                "name": "away/socks.png",
                "color": "ffffffff",
                "x": 5.51,
                "y": 0.76,
                "rotation": 110.01,
                "width": 11,
                "height": 14
            },
            "number": {
                "name": "../../player/kit/number.png",
                "color": "c30e2eff",
                "x": 17.18,
                "y": 0.16,
                "rotation": -89.44,
                "width": 33,
                "height": 18
            },
            "pelvis_shorts": {
                "name": "../../player/kit/shorts.png",
                "color": "4da56eff",
                "x": -1.27,
                "y": 0.02,
                "width": 55,
                "height": 8
            }
        }
    },
    "id": "lebanon",
    "kitColors": {
        "home": "c30e2e",
        "away": "e1e2e4"
    },
    "players": [
        {
            "race": "arab",
            "role": "G",
            "skin": {
                "eyebrows": {
                    "name": "../../player/eyebrows/02.png",
                    "color": "4f301cff",
                    "x": 39.24248552848485,
                    "y": -10.004341841886413,
                    "rotation": -90.13,
                    "width": 34,
                    "height": 4
                },
                "eyes": {
                    "name": "../../player/eyes/26.png",
                    "x": 31.885256563828822,
                    "y": -10.449992423394113,
                    "rotation": -90.13,
                    "width": 37,
                    "height": 12
                },
                "eyes_closed": {
                    "name": "../../player/eyes/closed/closed.png",
                    "x": 34.80248295446876,
                    "y": -10.206610767967252,
                    "rotation": -90.13,
                    "width": 38,
                    "height": 12
                },
                "eyes_dead": {
                    "name": "../../player/eyes/dead/dead.png",
                    "x": 30.134315682489962,
                    "y": -10.862687396912603,
                    "rotation": -90.13,
                    "width": 60,
                    "height": 40
                },
                "hair_front": {
                    "name": "../../player/hair/58.png",
                    "color": "5c483eff",
                    "x": 47.32388633870608,
                    "y": -4.160605472050706,
                    "rotation": -90.13,
                    "width": 76,
                    "height": 56
                },
                "hair_back": {
                    "name": "../../player/hair/58_back.png",
                    "color": "5c483eff",
                    "x": 32.48870041487743,
                    "y": -4.960280923504838,
                    "rotation": -90.13,
                    "width": 79,
                    "height": 90
                },
                "mouth_normal": {
                    "name": "../../player/mouth/16.png",
                    "x": 6.632147545180612,
                    "y": -12.465419402779661,
                    "rotation": -90.13,
                    "width": 26,
                    "height": 4
                },
                "mouth_smile": {
                    "name": "../../player/mouth/smile/01.png",
                    "x": 5.7156723152021,
                    "y": -12.380006435040233,
                    "rotation": -90.13,
                    "width": 32,
                    "height": 8
                },
                "mouth_dead": {
                    "name": "../../player/mouth/dead/01.png",
                    "x": 5.219076991331406,
                    "y": -10.878875833023953,
                    "rotation": -90.13,
                    "width": 23,
                    "height": 16
                },
                "nose": {
                    "name": "../../player/nose/04.png",
                    "color": "c74c85ff",
                    "x": 22.61304632496483,
                    "y": -10.460014800592536,
                    "rotation": -90.13,
                    "width": 19,
                    "height": 20
                },
                "face_accessory_2": {
                    "name": "../../player/accessories/face/beard_02.png",
                    "color": "ffffffff",
                    "x": 10.731920082034314,
                    "y": -5.224702845893112,
                    "rotation": -90.13,
                    "width": 70,
                    "height": 44
                }
            }
        },
        {
            "race": "arab",
            "role": "D",
            "skin": {
                "eyebrows": {
                    "name": "../../player/eyebrows/21.png",
                    "color": "331d11ff",
                    "x": 39.240216602404004,
                    "y": -11.004339267870316,
                    "rotation": -90.13,
                    "width": 34,
                    "height": 5
                },
                "eyes": {
                    "name": "../../player/eyes/06.png",
                    "x": 32.883552295252095,
                    "y": -11.202259418962885,
                    "rotation": -90.13,
                    "width": 40,
                    "height": 14
                },
                "eyes_closed": {
                    "name": "../../player/eyes/closed/closed.png",
                    "x": 32.80135363946052,
                    "y": -10.702071628797526,
                    "rotation": -90.13,
                    "width": 38,
                    "height": 12
                },
                "eyes_dead": {
                    "name": "../../player/eyes/dead/dead.png",
                    "x": 29.801361361508803,
                    "y": -10.695264850555008,
                    "rotation": -90.13,
                    "width": 60,
                    "height": 40
                },
                "hair_front": {
                    "name": "../../player/hair/26.png",
                    "color": "5c483dff",
                    "x": 54.00225863001647,
                    "y": 0.9909217216605474,
                    "rotation": -90.13,
                    "width": 65,
                    "height": 51
                },
                "hair_back": {
                    "name": "../../player/hair/26_back.png",
                    "color": "5c483dff",
                    "x": 36.98982329484543,
                    "y": -4.470492377876663,
                    "rotation": -90.13,
                    "width": 70,
                    "height": 90
                },
                "mouth_normal": {
                    "name": "../../player/mouth/17.png",
                    "x": 4.3842331856242565,
                    "y": -11.543650011945859,
                    "rotation": -90.13,
                    "width": 29,
                    "height": 8
                },
                "mouth_smile": {
                    "name": "../../player/mouth/smile/01.png",
                    "x": 5.221345917412246,
                    "y": -9.878878407040045,
                    "rotation": -90.13,
                    "width": 32,
                    "height": 8
                },
                "mouth_dead": {
                    "name": "../../player/mouth/dead/01.png",
                    "x": 3.223619991525272,
                    "y": -8.87434312889446,
                    "rotation": -90.13,
                    "width": 23,
                    "height": 16
                },
                "nose": {
                    "name": "../../player/nose/05.png",
                    "color": "6bbcffff",
                    "x": 20.110216602404012,
                    "y": -11.704339267870317,
                    "rotation": -90.13,
                    "width": 17,
                    "height": 22
                }
            }
        },
        {
            "race": "arab",
            "role": "D",
            "skin": {
                "eyebrows": {
                    "name": "../../player/eyebrows/26.png",
                    "color": "24150dff",
                    "x": 39.48170748609684,
                    "y": -14.754896846830178,
                    "rotation": -90.13,
                    "width": 35,
                    "height": 5
                },
                "eyes": {
                    "name": "../../player/eyes/28.png",
                    "x": 33.54794831982719,
                    "y": -12.203769462334016,
                    "rotation": -90.13,
                    "width": 41,
                    "height": 13
                },
                "eyes_closed": {
                    "name": "../../player/eyes/closed/closed.png",
                    "x": 34.79454171318582,
                    "y": -13.706601758910926,
                    "rotation": -90.13,
                    "width": 38,
                    "height": 12
                },
                "eyes_dead": {
                    "name": "../../player/eyes/dead/dead.png",
                    "x": 31.293416259201724,
                    "y": -14.198659230619942,
                    "rotation": -90.13,
                    "width": 60,
                    "height": 40
                },
                "hair_front": {
                    "name": "../../player/hair/12.png",
                    "color": "57453bff",
                    "x": 52.49091786063641,
                    "y": -4.005662019137728,
                    "rotation": -90.13,
                    "width": 74,
                    "height": 59
                },
                "hair_back": {
                    "name": "../../player/hair/12_back.png",
                    "color": "57453bff",
                    "x": 39.48868239676477,
                    "y": -4.976163406070716,
                    "rotation": -90.13,
                    "width": 75,
                    "height": 85
                },
                "mouth_normal": {
                    "name": "../../player/mouth/05.png",
                    "x": 10.462823931024607,
                    "y": -13.640780616404106,
                    "rotation": -90.13,
                    "width": 26,
                    "height": 9
                },
                "mouth_smile": {
                    "name": "../../player/mouth/smile/01.png",
                    "x": 5.7156723152021,
                    "y": -12.380006435040233,
                    "rotation": -90.13,
                    "width": 32,
                    "height": 8
                },
                "mouth_dead": {
                    "name": "../../player/mouth/dead/01.png",
                    "x": 5.7156723152021,
                    "y": -12.380006435040233,
                    "rotation": -90.13,
                    "width": 23,
                    "height": 16
                },
                "nose": {
                    "name": "../../player/nose/01.png",
                    "color": "148ab5ff",
                    "x": 22.603970620641473,
                    "y": -14.460004504528163,
                    "rotation": -90.13,
                    "width": 16,
                    "height": 21
                },
                "face_accessory_2": {
                    "name": "../../player/accessories/face/beard_02.png",
                    "color": "ffffffff",
                    "x": 10.731920082034314,
                    "y": -5.224702845893112,
                    "rotation": -90.13,
                    "width": 70,
                    "height": 44
                }
            }
        },
        {
            "race": "arab",
            "role": "M",
            "skin": {
                "eyebrows": {
                    "name": "../../player/eyebrows/01.png",
                    "color": "2b1a0eff",
                    "x": 40.73964550985966,
                    "y": -11.257742013487556,
                    "rotation": -90.13,
                    "width": 42,
                    "height": 5
                },
                "eyes": {
                    "name": "../../player/eyes/23.png",
                    "x": 31.047387523347215,
                    "y": -12.448096503627893,
                    "rotation": -90.13,
                    "width": 42,
                    "height": 18
                },
                "eyes_closed": {
                    "name": "../../player/eyes/closed/closed.png",
                    "x": 33.79794767632317,
                    "y": -12.204336693854227,
                    "rotation": -90.13,
                    "width": 38,
                    "height": 12
                },
                "eyes_dead": {
                    "name": "../../player/eyes/dead/dead.png",
                    "x": 31.297954111363403,
                    "y": -12.198664378652127,
                    "rotation": -90.13,
                    "width": 60,
                    "height": 40
                },
                "hair_front": {
                    "name": "../../player/hair/06.png",
                    "color": "4a2511ff",
                    "x": 50.65834555502619,
                    "y": -3.668169845994882,
                    "rotation": -90.13,
                    "width": 76,
                    "height": 48
                },
                "hair_back": {
                    "name": "../../player/hair/06_back.png",
                    "color": "4a2511ff",
                    "x": 33.656876695912565,
                    "y": -4.2962630532765385,
                    "rotation": -90.13,
                    "width": 77,
                    "height": 83
                },
                "mouth_normal": {
                    "name": "../../player/mouth/27B.png",
                    "x": 5.968507829299126,
                    "y": -11.13057688408056,
                    "rotation": -90.13,
                    "width": 23,
                    "height": 9
                },
                "mouth_smile": {
                    "name": "../../player/mouth/smile/01.png",
                    "x": 4.7190782783394525,
                    "y": -10.877741369983532,
                    "rotation": -90.13,
                    "width": 32,
                    "height": 8
                },
                "mouth_dead": {
                    "name": "../../player/mouth/dead/01.png",
                    "x": 4.717943815299033,
                    "y": -11.377740082975485,
                    "rotation": -90.13,
                    "width": 23,
                    "height": 16
                },
                "nose": {
                    "name": "../../player/nose/09.png",
                    "color": "a62458ff",
                    "x": 20.35567810673831,
                    "y": -13.704901351358341,
                    "rotation": -90.13,
                    "width": 15,
                    "height": 16
                },
                "face_accessory_2": {
                    "name": "../../player/accessories/face/beard_02C.png",
                    "color": "ffffffff",
                    "x": 10.23078690600195,
                    "y": -5.723567095844634,
                    "rotation": -90.13,
                    "width": 68,
                    "height": 42
                }
            }
        },
        {
            "race": "arab",
            "role": "A",
            "skin": {
                "eyebrows": {
                    "name": "../../player/eyebrows/29.png",
                    "color": "331f12ff",
                    "x": 39.98851297733131,
                    "y": -11.756039031918878,
                    "rotation": -90.13,
                    "width": 36,
                    "height": 4
                },
                "eyes": {
                    "name": "../../player/eyes/11.png",
                    "x": 31.296819648322984,
                    "y": -12.69866309164408,
                    "rotation": -90.13,
                    "width": 38,
                    "height": 18
                },
                "eyes_closed": {
                    "name": "../../player/eyes/closed/closed.png",
                    "x": 33.79908213936359,
                    "y": -11.704337980862272,
                    "rotation": -90.13,
                    "width": 38,
                    "height": 12
                },
                "eyes_dead": {
                    "name": "../../player/eyes/dead/dead.png",
                    "x": 30.799089861411872,
                    "y": -11.697531202619754,
                    "rotation": -90.13,
                    "width": 60,
                    "height": 40
                },
                "hair_front": {
                    "name": "../../player/hair/27.png",
                    "color": "574338ff",
                    "x": 48.99206133273315,
                    "y": -3.4977220648628347,
                    "rotation": -90.13,
                    "width": 72,
                    "height": 40
                },
                "hair_back": {
                    "name": "../../player/hair/27_back.png",
                    "color": "574338ff",
                    "x": 29.989841312958077,
                    "y": -4.454609895310783,
                    "rotation": -90.13,
                    "width": 72,
                    "height": 76
                },
                "mouth_normal": {
                    "name": "../../player/mouth/03B.png",
                    "x": 8.211695259520399,
                    "y": -14.135674245714169,
                    "rotation": -90.13,
                    "width": 29,
                    "height": 6
                },
                "mouth_smile": {
                    "name": "../../player/mouth/smile/01.png",
                    "x": 5.216808065250566,
                    "y": -11.878873259007861,
                    "rotation": -90.13,
                    "width": 32,
                    "height": 8
                },
                "mouth_dead": {
                    "name": "../../player/mouth/dead/01.png",
                    "x": 3.719080852355545,
                    "y": -10.875472443902693,
                    "rotation": -90.13,
                    "width": 23,
                    "height": 16
                },
                "nose": {
                    "name": "../../player/nose/14.png",
                    "color": "20ab9fff",
                    "x": 19.60284387964933,
                    "y": -14.953196439277598,
                    "rotation": -90.13,
                    "width": 15,
                    "height": 21
                }
            }
        },
        {
            "race": "arab",
            "role": "A",
            "skin": {
                "eyebrows": {
                    "name": "../../player/eyebrows/30.png",
                    "color": "301e13ff",
                    "x": 38.82166023651001,
                    "y": -11.836725070323224,
                    "rotation": -90.13,
                    "width": 36,
                    "height": 6
                },
                "eyes": {
                    "name": "../../player/eyes/01.png",
                    "x": 32.217265498942965,
                    "y": -11.034080563911672,
                    "rotation": -90.13,
                    "width": 41,
                    "height": 17
                },
                "eyes_closed": {
                    "name": "../../player/eyes/closed/closed.png",
                    "x": 33.297948963331216,
                    "y": -12.203202230813806,
                    "rotation": -90.13,
                    "width": 38,
                    "height": 12
                },
                "eyes_dead": {
                    "name": "../../player/eyes/dead/dead.png",
                    "x": 31.297954111363403,
                    "y": -12.198664378652127,
                    "rotation": -90.13,
                    "width": 60,
                    "height": 40
                },
                "hair_front": {
                    "name": "../../player/hair/09C.png",
                    "color": "ffffffff",
                    "x": 48.49886939798372,
                    "y": -0.49659532387069366,
                    "rotation": -90.13,
                    "width": 62,
                    "height": 38
                },
                "hair_back": {
                    "name": "../../player/hair/09C_back.png",
                    "color": "ffffffff",
                    "x": 31.487568525853103,
                    "y": -5.458010710415951,
                    "rotation": -90.13,
                    "width": 70,
                    "height": 72
                },
                "mouth_normal": {
                    "name": "../../player/mouth/14.png",
                    "x": 7.549757238199543,
                    "y": -12.050833657527138,
                    "rotation": -90.13,
                    "width": 25,
                    "height": 9
                },
                "mouth_smile": {
                    "name": "../../player/mouth/smile/01.png",
                    "x": 5.217942528290986,
                    "y": -11.378874546015906,
                    "rotation": -90.13,
                    "width": 32,
                    "height": 8
                },
                "mouth_dead": {
                    "name": "../../player/mouth/dead/01.png",
                    "x": 3.7196480838757555,
                    "y": -10.625473087406716,
                    "rotation": -90.13,
                    "width": 23,
                    "height": 16
                },
                "nose": {
                    "name": "../../player/nose/25.png",
                    "color": "4a80c2ff",
                    "x": 21.357377227282846,
                    "y": -12.957172207951253,
                    "rotation": -90.13,
                    "width": 19,
                    "height": 19
                },
                "face_accessory_2": {
                    "name": "../../player/accessories/face/beard_02C.png",
                    "color": "ffffffff",
                    "x": 10.23078690600195,
                    "y": -5.723567095844634,
                    "rotation": -90.13,
                    "width": 68,
                    "height": 42
                }
            }
        }
    ]
}
